pydensecrf/__init__.py
pydensecrf/densecrf.cpython-39-darwin.so
pydensecrf/eigen.cpython-39-darwin.so
pydensecrf/utils.py
pydensecrf2-1.1rc1.dist-info/LICENSE
pydensecrf2-1.1rc1.dist-info/METADATA
pydensecrf2-1.1rc1.dist-info/WHEEL
pydensecrf2-1.1rc1.dist-info/top_level.txt
pydensecrf2-1.1rc1.dist-info/RECORD
